__init__.py
calc.py
data.py
image_au.py
plot.py
ppprocess-0.0.3.dist-info/METADATA
ppprocess-0.0.3.dist-info/WHEEL
ppprocess-0.0.3.dist-info/top_level.txt
ppprocess-0.0.3.dist-info/RECORD
