Metadata-Version: 2.1
Name: ppprocess
Version: 0.0.3
Summary: My utils for AI
Home-page: https://github.com/cuongdtone/ppprocess
Author: Cuong Tran
Author-email: cuongtran73d1@gmail.com
Classifier: Programming Language :: Python :: 3
Classifier: License :: OSI Approved :: MIT License
Classifier: Operating System :: OS Independent
Requires-Python: >=3.6
